CMakeLists.txt
LICENSE
MANIFEST.in
README.md
setup.py
gobuild/.gitkeep
hysteria2/__init__.py
hysteria2-go/.gitignore
hysteria2-go/CHANGELOG.md
hysteria2-go/Dockerfile
hysteria2-go/LICENSE.md
hysteria2-go/PROTOCOL.md
hysteria2-go/README.md
hysteria2-go/go.work
hysteria2-go/go.work.sum
hysteria2-go/hyperbole.py
hysteria2-go/logo.svg
hysteria2-go/platforms.txt
hysteria2-go/requirements.txt
hysteria2-go/.github/FUNDING.yml
hysteria2-go/.github/dependabot.yml
hysteria2-go/.github/ISSUE_TEMPLATE/bug_report.md
hysteria2-go/.github/ISSUE_TEMPLATE/bug_report.zh.md
hysteria2-go/.github/ISSUE_TEMPLATE/feature_request.md
hysteria2-go/.github/ISSUE_TEMPLATE/feature_request.zh.md
hysteria2-go/.github/workflows/autotag.yaml
hysteria2-go/.github/workflows/docker.yml
hysteria2-go/.github/workflows/master.yml
hysteria2-go/.github/workflows/release.yml
hysteria2-go/.github/workflows/scripts.yml
hysteria2-go/app/LICENSE.md
hysteria2-go/app/go.mod
hysteria2-go/app/go.sum
hysteria2-go/app/main.go
hysteria2-go/app/pprof.go
hysteria2-go/app/cmd/client.go
hysteria2-go/app/cmd/client_test.go
hysteria2-go/app/cmd/client_test.yaml
hysteria2-go/app/cmd/errors.go
hysteria2-go/app/cmd/ping.go
hysteria2-go/app/cmd/root.go
hysteria2-go/app/cmd/server.go
hysteria2-go/app/cmd/server_test.go
hysteria2-go/app/cmd/server_test.yaml
hysteria2-go/app/cmd/share.go
hysteria2-go/app/cmd/speedtest.go
hysteria2-go/app/cmd/update.go
hysteria2-go/app/cmd/version.go
hysteria2-go/app/internal/forwarding/tcp.go
hysteria2-go/app/internal/forwarding/tcp_test.go
hysteria2-go/app/internal/forwarding/udp.go
hysteria2-go/app/internal/forwarding/udp_test.go
hysteria2-go/app/internal/http/server.go
hysteria2-go/app/internal/http/server_test.go
hysteria2-go/app/internal/http/server_test.py
hysteria2-go/app/internal/http/test.crt
hysteria2-go/app/internal/http/test.key
hysteria2-go/app/internal/proxymux/.mockery.yaml
hysteria2-go/app/internal/proxymux/manager.go
hysteria2-go/app/internal/proxymux/manager_test.go
hysteria2.egg-info/PKG-INFO
hysteria2.egg-info/SOURCES.txt
hysteria2.egg-info/dependency_links.txt
hysteria2.egg-info/not-zip-safe
hysteria2.egg-info/top_level.txt
